{
"type": "FeatureCollection",
"features": [
{ "type": "Feature", "properties": { "OBJECTID": 73, "ID_SITE": "E6311", "CITY": "الخبر", "COORDINATES_E": 50.141434, "COORDINATES_N": 26.10976, "COMPANY_SERVICE_NAME": "موبايلي", "REGION_ID": 5, "GOVERNORATE_ID": 506, "AMANA_ID": 503, "SUBMUNICIPALITY_ID": null, "MUNICIPALITY_ID": 5039.0, "DISTRICT_ID": 5039016.0, "DISTRICTBALADI": 5988, "MUNICIPALITYBALADI": 6001003, "AMANABALADI": 6001 }, "geometry": { "type": "Point", "coordinates": [ 50.141434, 26.10976 ] } },
{ "type": "Feature", "properties": { "OBJECTID": 83, "ID_SITE": "E6495", "CITY": "الخبر", "COORDINATES_E": 50.2172, "COORDINATES_N": 26.3261, "COMPANY_SERVICE_NAME": "موبايلي", "REGION_ID": 5, "GOVERNORATE_ID": 506, "AMANA_ID": 503, "SUBMUNICIPALITY_ID": null, "MUNICIPALITY_ID": 5039.0, "DISTRICT_ID": 5039008.0, "DISTRICTBALADI": 563, "MUNICIPALITYBALADI": 6001003, "AMANABALADI": 6001 }, "geometry": { "type": "Point", "coordinates": [ 50.2172, 26.3261 ] } },
{ "type": "Feature", "properties": { "OBJECTID": 64, "ID_SITE": "E5178", "CITY": "الخبر", "COORDINATES_E": 50.221816, "COORDINATES_N": 26.356212, "COMPANY_SERVICE_NAME": "موبايلي", "REGION_ID": 5, "GOVERNORATE_ID": 506, "AMANA_ID": 503, "SUBMUNICIPALITY_ID": null, "MUNICIPALITY_ID": 5039.0, "DISTRICT_ID": 5039044.0, "DISTRICTBALADI": 5997, "MUNICIPALITYBALADI": 6001003, "AMANABALADI": 6001 }, "geometry": { "type": "Point", "coordinates": [ 50.221816, 26.356212 ] } },
{ "type": "Feature", "properties": { "OBJECTID": 51, "ID_SITE": "6311", "CITY": "الخبر", "COORDINATES_E": 50.141434, "COORDINATES_N": 26.10976, "COMPANY_SERVICE_NAME": "موبايلي", "REGION_ID": 5, "GOVERNORATE_ID": 506, "AMANA_ID": 503, "SUBMUNICIPALITY_ID": null, "MUNICIPALITY_ID": 5039.0, "DISTRICT_ID": 5039016.0, "DISTRICTBALADI": 5988, "MUNICIPALITYBALADI": 6001003, "AMANABALADI": 6001 }, "geometry": { "type": "Point", "coordinates": [ 50.141434, 26.10976 ] } }
]
}
